wagtail_site_inheritance/__init__.py
wagtail_site_inheritance/admin.py
wagtail_site_inheritance/forms.py
wagtail_site_inheritance/models.py
wagtail_site_inheritance/permissions.py
wagtail_site_inheritance/receivers.py
wagtail_site_inheritance/views.py
wagtail_site_inheritance/wagtail_forms.py
wagtail_site_inheritance/wagtail_hooks.py
wagtail_site_inheritance/locale/nl/LC_MESSAGES/django.mo
wagtail_site_inheritance/locale/nl/LC_MESSAGES/django.po
wagtail_site_inheritance/migrations/0001_initial.py
wagtail_site_inheritance/migrations/__init__.py
wagtail_site_inheritance-1.1.0.dist-info/LICENSE
wagtail_site_inheritance-1.1.0.dist-info/METADATA
wagtail_site_inheritance-1.1.0.dist-info/WHEEL
wagtail_site_inheritance-1.1.0.dist-info/top_level.txt
wagtail_site_inheritance-1.1.0.dist-info/RECORD
