Metadata-Version: 2.1
Name: wagtail-site-inheritance
Version: 1.1.0
Summary: Site Inheritance for Wagtail
Home-page: https://github.com/labd/wagtail-site-inheritance
Author: Lab Digital
Author-email: opensource@labdigital.nl
License: MIT
Platform: UNKNOWN
Classifier: Development Status :: 5 - Production/Stable
Classifier: Environment :: Web Environment
Classifier: Framework :: Django
Classifier: Framework :: Django :: 3.2
Classifier: Framework :: Django :: 4.0
Classifier: Framework :: Wagtail
Classifier: Framework :: Wagtail :: 2
Classifier: Framework :: Wagtail :: 3
Classifier: License :: OSI Approved :: MIT License
Classifier: Programming Language :: Python
Classifier: Programming Language :: Python :: 3.8
Classifier: Programming Language :: Python :: 3.9
Classifier: Programming Language :: Python :: 3.10
Requires-Dist: Django (>=2.2)
Requires-Dist: wagtail (<4.0,>=2.16)
Provides-Extra: docs
Requires-Dist: sphinx (>=1.4.0) ; extra == 'docs'
Provides-Extra: test
Requires-Dist: coverage[toml] (==5.2.1) ; extra == 'test'
Requires-Dist: factory-boy (==3.2.0) ; extra == 'test'
Requires-Dist: freezegun (==1.1.0) ; extra == 'test'
Requires-Dist: pytest (==6.2.4) ; extra == 'test'
Requires-Dist: pytest-django (==4.4.0) ; extra == 'test'
Requires-Dist: pytest-cov (==2.12.1) ; extra == 'test'
Requires-Dist: wagtail-factories (==2.0.1) ; extra == 'test'
Requires-Dist: mock (==4.0.3) ; extra == 'test'
Requires-Dist: isort[pyproject] (==4.3.21) ; extra == 'test'
Requires-Dist: flake8 (==3.7.9) ; extra == 'test'
Requires-Dist: flake8-blind-except (==0.1.1) ; extra == 'test'
Requires-Dist: flake8-debugger (==3.1.0) ; extra == 'test'
